ichandbook/__init__.py
ichandbook/document.py
ichandbook/link_validator.py
ichandbook/markdown_page.py
ichandbook-0.0.1.dist-info/LICENSE
ichandbook-0.0.1.dist-info/METADATA
ichandbook-0.0.1.dist-info/WHEEL
ichandbook-0.0.1.dist-info/top_level.txt
ichandbook-0.0.1.dist-info/RECORD
