Metadata-Version: 2.1
Name: ichandbook
Version: 0.0.1
Summary: Library to help formating and publication of organisation technical handbook.
Author-email: "James Grogan, Irish Centre for High End Computing" <james.grogan@ichec.ie>
Project-URL: Repository, https://git.ichec.ie/performance/toolshed/ichandbook
Project-URL: Homepage, https://git.ichec.ie/performance/toolshed/ichandbook
Keywords: Publishing,Markdown,Handbook
Classifier: Development Status :: 3 - Alpha
Classifier: Programming Language :: Python :: 3
Classifier: License :: OSI Approved :: GNU General Public License v3 or later (GPLv3+)
Classifier: Operating System :: OS Independent
Classifier: Topic :: System :: Distributed Computing
Requires-Python: >=3.8
License-File: LICENSE
Requires-Dist: markdown
Requires-Dist: beautifulsoup4
Requires-Dist: pyspelling
Provides-Extra: test
Requires-Dist: pytest ; extra == 'test'
Requires-Dist: pytest-cov ; extra == 'test'
Requires-Dist: pytest-sugar ; extra == 'test'
Requires-Dist: black ; extra == 'test'
Requires-Dist: mypy ; extra == 'test'
